{"@context":["https://www.w3.org/ns/did/v1","https://w3id.org/security/suites/jws-2020/v1"],"id":"did:web:tng-cdn-uat.who.int:v2:trustlist-ref:-:IRL:SCA","controller":"did:web:tng-cdn-uat.who.int:v2:trustlist-ref:-:IRL","verificationMethod":["did:web:tng-cdn-uat.who.int:v2:trustlist:-:IRL:SCA"],"proof":{"type":"JsonWebSignature2020","created":"2025-06-13T12:00:28Z","nonce":"2iG71TwBVQ1SPZclvv26mOeztsdywZ7L","proofPurpose":"assertionMethod","verificationMethod":"did:web:raw.githubusercontent.com:WorldHealthOrganization:tng-participants-uat:main:WHO:signing:DID","jws":"eyJiNjQiOmZhbHNlLCJjcml0IjpbImI2NCJdLCJhbGciOiJFUzI1NiJ9..MEQCIBJxk7Eab9kkaUZN33QK2q2QI0d1NHKUlWQeZLA44-VzAiA2Fi3eBPS8JhryZ3GSh0juFecnEbQIjhBGqTSLFAE3yA"}}