{"@context":["https://www.w3.org/ns/did/v1","https://w3id.org/security/suites/jws-2020/v1"],"id":"did:web:tng-cdn-uat.who.int:v2:trustlist-ref:DCC:MCO","controller":"did:web:tng-cdn-uat.who.int:v2:trustlist-ref:DCC","verificationMethod":["did:web:tng-cdn-uat.who.int:v2:trustlist-ref:DCC:MCO:SCA"],"proof":{"type":"JsonWebSignature2020","created":"2026-05-05T00:00:37Z","nonce":"JRfTYYmC8IAsx1XYJOlwxovVeiNv3ax5","proofPurpose":"assertionMethod","verificationMethod":"did:web:raw.githubusercontent.com:WorldHealthOrganization:tng-participants-uat:main:WHO:signing:DID","jws":"eyJiNjQiOmZhbHNlLCJjcml0IjpbImI2NCJdLCJhbGciOiJFUzI1NiJ9..MEUCIChmZGMorSps4N9oeIN-YLTTguhHZHaxa7SAW2__xvX9AiEAwLXGGGYPh_X8BOOOCofy3VDTv1Dy_Iw_dq4wpEz-eWg"}}