{"@context":["https://www.w3.org/ns/did/v1","https://w3id.org/security/suites/jws-2020/v1"],"id":"did:web:tng-cdn-uat.who.int:v2:trustlist-ref:-:XV:SCA","controller":"did:web:tng-cdn-uat.who.int:v2:trustlist-ref:-:XV","verificationMethod":["did:web:tng-cdn-uat.who.int:v2:trustlist:-:XV:SCA"],"proof":{"type":"JsonWebSignature2020","created":"2025-10-11T12:00:38Z","nonce":"2ZccQmtu4kcrqt7EgymRNwQ8SZQdT0N7","proofPurpose":"assertionMethod","verificationMethod":"did:web:raw.githubusercontent.com:WorldHealthOrganization:tng-participants-uat:main:WHO:signing:DID","jws":"eyJiNjQiOmZhbHNlLCJjcml0IjpbImI2NCJdLCJhbGciOiJFUzI1NiJ9..MEYCIQCQWjZN_LfL6PwVi1DuMXUsi-obqv9LZMzz_tPnalqsfgIhAJA5LdB0zisx6jdC93AyQ6QAwqgccljoRdNyknJ-pBxw"}}