{"@context":["https://www.w3.org/ns/did/v1","https://w3id.org/security/suites/jws-2020/v1"],"id":"did:web:tng-cdn-uat.who.int:v2:trustlist-ref:IPS-PILGRIMAGE:XU:SCA","controller":"did:web:tng-cdn-uat.who.int:v2:trustlist-ref:IPS-PILGRIMAGE:XU","verificationMethod":["did:web:tng-cdn-uat.who.int:v2:trustlist:IPS-PILGRIMAGE:XU:SCA"],"proof":{"type":"JsonWebSignature2020","created":"2025-09-06T12:00:28Z","nonce":"cpIyzUuY3gWNffs5XauftkaVlKjEyKSA","proofPurpose":"assertionMethod","verificationMethod":"did:web:raw.githubusercontent.com:WorldHealthOrganization:tng-participants-uat:main:WHO:signing:DID","jws":"eyJiNjQiOmZhbHNlLCJjcml0IjpbImI2NCJdLCJhbGciOiJFUzI1NiJ9..MEUCIQCFkZ0-IumzmPTjVvx_dtFTTCgbvTogB5EyjFYhe3QVogIgP9YPU6GFa4xkeEpSzi4tl20L8FqN0ikCGajdhZi7AxM"}}