{"@context":["https://www.w3.org/ns/did/v1","https://w3id.org/security/suites/jws-2020/v1"],"id":"did:web:tng-cdn-uat.who.int:v2:trustlist-ref:-:ALB:DSC","controller":"did:web:tng-cdn-uat.who.int:v2:trustlist-ref:-:ALB","verificationMethod":["did:web:tng-cdn-uat.who.int:v2:trustlist:-:ALB:DSC"],"proof":{"type":"JsonWebSignature2020","created":"2025-08-25T12:00:36Z","nonce":"1CyWJxSn99C75NFdq8vXjfVc2ytwk4BM","proofPurpose":"assertionMethod","verificationMethod":"did:web:raw.githubusercontent.com:WorldHealthOrganization:tng-participants-uat:main:WHO:signing:DID","jws":"eyJiNjQiOmZhbHNlLCJjcml0IjpbImI2NCJdLCJhbGciOiJFUzI1NiJ9..MEYCIQCF3TIa_MaQzVKc5TI8UU4-T6qcL0kFHsBwiMbQ0eTCZQIhANdxj7gxET3ag2PFigG1fn4tfmUFtXgR2wftdVZ3VMGL"}}