{"@context":["https://www.w3.org/ns/did/v1","https://w3id.org/security/suites/jws-2020/v1"],"id":"did:web:tng-cdn-uat.who.int:v2:trustlist-ref:-:-:DSC","controller":"did:web:tng-cdn-uat.who.int:v2:trustlist-ref:-:-","verificationMethod":["did:web:tng-cdn-uat.who.int:v2:trustlist:-:-:DSC"],"proof":{"type":"JsonWebSignature2020","created":"2025-06-19T12:00:28Z","nonce":"wPoa6xmLzwU6nI1B3OHnmqghZbeJ0pHZ","proofPurpose":"assertionMethod","verificationMethod":"did:web:raw.githubusercontent.com:WorldHealthOrganization:tng-participants-uat:main:WHO:signing:DID","jws":"eyJiNjQiOmZhbHNlLCJjcml0IjpbImI2NCJdLCJhbGciOiJFUzI1NiJ9..MEQCIAtibr7k0ljWmOIItrLkHgIQzKURgxgqSD4KxDoMNtqmAiAuEWZ09l-t07203NRxQRrZLLViQljPJRX3Oy_t79xCLw"}}