{"@context":["https://www.w3.org/ns/did/v1","https://w3id.org/security/suites/jws-2020/v1"],"id":"did:web:tng-cdn-uat.who.int:v2:trustlist-ref:-:ESP","controller":"did:web:tng-cdn-uat.who.int:v2:trustlist-ref:-","verificationMethod":["did:web:tng-cdn-uat.who.int:v2:trustlist-ref:-:ESP:SCA","did:web:tng-cdn-uat.who.int:v2:trustlist-ref:-:ESP:DSC"],"proof":{"type":"JsonWebSignature2020","created":"2025-06-30T00:00:40Z","nonce":"aiDLzq0TDZUzTdoEyDiSmsA52Fr5QkhN","proofPurpose":"assertionMethod","verificationMethod":"did:web:raw.githubusercontent.com:WorldHealthOrganization:tng-participants-uat:main:WHO:signing:DID","jws":"eyJiNjQiOmZhbHNlLCJjcml0IjpbImI2NCJdLCJhbGciOiJFUzI1NiJ9..MEUCIQC9Ix2zp8N9fShVZz-Ivk1PCMEazpuD2ervo9YlnGz8AwIgYCxTkRjA9QS56R-c2_bUOZkoACdiXVLRj7m7tyyua0o"}}