{"@context":["https://www.w3.org/ns/did/v1","https://w3id.org/security/suites/jws-2020/v1"],"id":"did:web:tng-cdn-uat.who.int:v2:trustlist","controller":"did:web:tng-cdn-uat.who.int:v2:trustlist","verificationMethod":[],"proof":{"type":"JsonWebSignature2020","created":"2025-03-02T12:00:00Z","nonce":"TYbTw2TElDDqrZ6t9z9yCyRc3ktJm250","proofPurpose":"assertionMethod","verificationMethod":"did:web:raw.githubusercontent.com:WorldHealthOrganization:tng-participants-uat:main:WHO:signing:DID","jws":"eyJiNjQiOmZhbHNlLCJjcml0IjpbImI2NCJdLCJhbGciOiJFUzI1NiJ9..MEUCIFS72HDbVDaWh4_eh2LDspbGgKlZNXIQYletJzU8Gy2AAiEA7QRsvOnUhzh4pfGHbIcuchr1Z8qj4Y_BP2DmnmfTeJU"}}