{"@context":["https://www.w3.org/ns/did/v1","https://w3id.org/security/suites/jws-2020/v1"],"id":"did:web:tng-cdn-uat.who.int:v2:trustlist","controller":"did:web:tng-cdn-uat.who.int:v2:trustlist","verificationMethod":[],"proof":{"type":"JsonWebSignature2020","created":"2025-03-01T06:00:00Z","nonce":"qnyAZb6S7tcYYBwNRuNCp1MGZRaI353n","proofPurpose":"assertionMethod","verificationMethod":"did:web:raw.githubusercontent.com:WorldHealthOrganization:tng-participants-uat:main:WHO:signing:DID","jws":"eyJiNjQiOmZhbHNlLCJjcml0IjpbImI2NCJdLCJhbGciOiJFUzI1NiJ9..MEYCIQDhFXsadQXh1b71cQDJ4clXFIjl_Y8f4KGM6Ll7fKSm-gIhALWwtL9JMgiqxUB12ysadu3anbBaRlfLrCIguyWkMYpr"}}