{"@context":["https://www.w3.org/ns/did/v1","https://w3id.org/security/suites/jws-2020/v1","https://worldhealthorganization.github.io/smart-trust/tng-additional-context/v1"],"id":"did:web:tng-cdn-uat.who.int:v2:trustlist-ref:DCC:FRO:SCA","controller":"did:web:tng-cdn-uat.who.int:v2:trustlist-ref:DCC:FRO","verificationMethod":["did:web:tng-cdn-uat.who.int:v2:trustlist:DCC:FRO:SCA"],"proof":{"type":"JsonWebSignature2020","created":"2026-04-27T18:00:19Z","nonce":"6ZKh4G4bR9Dg46QmtOQLmq7PNFbbQUTb","proofPurpose":"assertionMethod","verificationMethod":"did:web:raw.githubusercontent.com:WorldHealthOrganization:tng-participants-uat:main:WHO:signing:DID","jws":"eyJiNjQiOmZhbHNlLCJjcml0IjpbImI2NCJdLCJhbGciOiJFUzI1NiJ9..MEYCIQDCTI_o7ztZrHoumAVSu2eNI0LGRl5iSDSBV-rnLZRE2gIhAPS3QyuXU4luIzEGjPsTztk7_VFU1X2LUmtMw2ciTsCq"}}