{"@context":["https://www.w3.org/ns/did/v1","https://w3id.org/security/suites/jws-2020/v1"],"id":"did:web:tng-cdn-uat.who.int:v2:trustlist-ref:DCC:PRT:SCA","controller":"did:web:tng-cdn-uat.who.int:v2:trustlist-ref:DCC:PRT","verificationMethod":["did:web:tng-cdn-uat.who.int:v2:trustlist:DCC:PRT:SCA"],"proof":{"type":"JsonWebSignature2020","created":"2025-10-25T12:00:15Z","nonce":"0NChb8W5auumegMLjKCYcFWW8YT4hXKp","proofPurpose":"assertionMethod","verificationMethod":"did:web:raw.githubusercontent.com:WorldHealthOrganization:tng-participants-uat:main:WHO:signing:DID","jws":"eyJiNjQiOmZhbHNlLCJjcml0IjpbImI2NCJdLCJhbGciOiJFUzI1NiJ9..MEUCIHInipSN20uA1HYS5XxwVJT2rMv_o2XK50au6Dq6vk8yAiEAqGfCpOIReTOhVhJjl5fKe_LYnEKOJzUB1Sg-NcU2fks"}}