{"@context":["https://www.w3.org/ns/did/v1","https://w3id.org/security/suites/jws-2020/v1"],"id":"did:web:tng-cdn-uat.who.int:v2:trustlist-ref:DCC:-:SCA","controller":"did:web:tng-cdn-uat.who.int:v2:trustlist-ref:DCC:-","verificationMethod":["did:web:tng-cdn-uat.who.int:v2:trustlist:DCC:-:SCA"],"proof":{"type":"JsonWebSignature2020","created":"2025-10-04T12:00:30Z","nonce":"sy4Li9oq06khvt24yf2Gpp0TB6TAz5Y3","proofPurpose":"assertionMethod","verificationMethod":"did:web:raw.githubusercontent.com:WorldHealthOrganization:tng-participants-uat:main:WHO:signing:DID","jws":"eyJiNjQiOmZhbHNlLCJjcml0IjpbImI2NCJdLCJhbGciOiJFUzI1NiJ9..MEQCICzJTZFHSLVtOu7m7kZjjw76LrXmEJs-f2mZz__udkSIAiBUoob9fa1r0d_jNehqic0VEOChQon4hFUQB3zbwfP2ZQ"}}