{"@context":["https://www.w3.org/ns/did/v1","https://w3id.org/security/suites/jws-2020/v1"],"id":"did:web:tng-cdn-uat.who.int:v2:trustlist-ref:-:TUR:SCA","controller":"did:web:tng-cdn-uat.who.int:v2:trustlist-ref:-:TUR","verificationMethod":["did:web:tng-cdn-uat.who.int:v2:trustlist:-:TUR:SCA"],"proof":{"type":"JsonWebSignature2020","created":"2025-10-25T12:00:16Z","nonce":"oK4sVbEGNBx488ipWUD13yyYDLzTUXBK","proofPurpose":"assertionMethod","verificationMethod":"did:web:raw.githubusercontent.com:WorldHealthOrganization:tng-participants-uat:main:WHO:signing:DID","jws":"eyJiNjQiOmZhbHNlLCJjcml0IjpbImI2NCJdLCJhbGciOiJFUzI1NiJ9..MEUCIQDe1Kq3lNp_tUOA7tAvIGILID-Lpr7C3Uy42VrpfbZA9QIgU_SNC9nHiJAM0Nt2QzPcrzk9xC-XnWhxTUJDOEEasLg"}}