{"@context":["https://www.w3.org/ns/did/v1","https://w3id.org/security/suites/jws-2020/v1"],"id":"did:web:tng-cdn-uat.who.int:v2:trustlist:-:WHO","controller":"did:web:tng-cdn-uat.who.int:v2:trustlist:-","verificationMethod":[],"proof":{"type":"JsonWebSignature2020","created":"2025-02-25T18:00:00Z","nonce":"Iyk8E93ZHETywgOTt9qjwPnQPztzUe2R","proofPurpose":"assertionMethod","verificationMethod":"did:web:raw.githubusercontent.com:WorldHealthOrganization:tng-participants-uat:main:WHO:signing:DID","jws":"eyJiNjQiOmZhbHNlLCJjcml0IjpbImI2NCJdLCJhbGciOiJFUzI1NiJ9..MEYCIQDapb-UKyAwZebo_AmtIziChSVlgO7MvOmXjmpuWWPd_AIhAPIHa9knxHoEJ7ICKiHYDVnFX73HiP_OT8XLZTh2vMTd"}}