{"@context":["https://www.w3.org/ns/did/v1","https://w3id.org/security/suites/jws-2020/v1"],"id":"did:web:tng-cdn-uat.who.int:v2:trustlist:-:WHO","controller":"did:web:tng-cdn-uat.who.int:v2:trustlist:-","verificationMethod":[],"proof":{"type":"JsonWebSignature2020","created":"2025-02-22T00:00:00Z","nonce":"qMsKIltcoxJ628u2lKCidbTpiLYfun9w","proofPurpose":"assertionMethod","verificationMethod":"did:web:raw.githubusercontent.com:WorldHealthOrganization:tng-participants-uat:main:WHO:signing:DID","jws":"eyJiNjQiOmZhbHNlLCJjcml0IjpbImI2NCJdLCJhbGciOiJFUzI1NiJ9..MEQCIDyfDfj9AqSgMIqZsjM8Xv55UkeVTXM1cjfDd8-HQD0VAiAb9NHCy_cVYtas_dMM6gTfH5ExhE04HMzIiIft2TLMDg"}}