{"@context":["https://www.w3.org/ns/did/v1","https://w3id.org/security/suites/jws-2020/v1"],"id":"did:web:tng-cdn-uat.who.int:v2:trustlist:-:WHO","controller":"did:web:tng-cdn-uat.who.int:v2:trustlist:-","verificationMethod":[],"proof":{"type":"JsonWebSignature2020","created":"2025-09-13T12:00:17Z","nonce":"ivEX7BFYhVdMIvkGl1pzbF05CGX2JbrZ","proofPurpose":"assertionMethod","verificationMethod":"did:web:raw.githubusercontent.com:WorldHealthOrganization:tng-participants-uat:main:WHO:signing:DID","jws":"eyJiNjQiOmZhbHNlLCJjcml0IjpbImI2NCJdLCJhbGciOiJFUzI1NiJ9..MEUCIBLCWjdfHbu8txRbozRmBxHjctUcxvzmET2kSsfGiHJrAiEAonb7tcr2izGOhXHvYXcdjEv_oIOWIgYr4M8zsvQ5g6w"}}