{"@context":["https://www.w3.org/ns/did/v1","https://w3id.org/security/suites/jws-2020/v1"],"id":"did:web:tng-cdn-uat.who.int:v2:trustlist-ref:DCC","controller":"did:web:tng-cdn-uat.who.int:v2:trustlist-ref","verificationMethod":["did:web:tng-cdn-uat.who.int:v2:trustlist-ref:DCC:XXA","did:web:tng-cdn-uat.who.int:v2:trustlist-ref:DCC:XX","did:web:tng-cdn-uat.who.int:v2:trustlist-ref:DCC:NZL","did:web:tng-cdn-uat.who.int:v2:trustlist-ref:DCC:FRO","did:web:tng-cdn-uat.who.int:v2:trustlist-ref:DCC:IRL","did:web:tng-cdn-uat.who.int:v2:trustlist-ref:DCC:XXB","did:web:tng-cdn-uat.who.int:v2:trustlist-ref:DCC:SAU","did:web:tng-cdn-uat.who.int:v2:trustlist-ref:DCC:SVK","did:web:tng-cdn-uat.who.int:v2:trustlist-ref:DCC:SVN","did:web:tng-cdn-uat.who.int:v2:trustlist-ref:DCC:LTU","did:web:tng-cdn-uat.who.int:v2:trustlist-ref:DCC:THA","did:web:tng-cdn-uat.who.int:v2:trustlist-ref:DCC:HRV","did:web:tng-cdn-uat.who.int:v2:trustlist-ref:DCC:XXO","did:web:tng-cdn-uat.who.int:v2:trustlist-ref:DCC:IDN","did:web:tng-cdn-uat.who.int:v2:trustlist-ref:DCC:YK","did:web:tng-cdn-uat.who.int:v2:trustlist-ref:DCC:PRT","did:web:tng-cdn-uat.who.int:v2:trustlist-ref:DCC:MLT","did:web:tng-cdn-uat.who.int:v2:trustlist-ref:DCC:CYP","did:web:tng-cdn-uat.who.int:v2:trustlist-ref:DCC:SWE","did:web:tng-cdn-uat.who.int:v2:trustlist-ref:DCC:ESP","did:web:tng-cdn-uat.who.int:v2:trustlist-ref:DCC:MYS","did:web:tng-cdn-uat.who.int:v2:trustlist-ref:DCC:EST","did:web:tng-cdn-uat.who.int:v2:trustlist-ref:DCC:BEL","did:web:tng-cdn-uat.who.int:v2:trustlist-ref:DCC:FIN","did:web:tng-cdn-uat.who.int:v2:trustlist-ref:DCC:BEN","did:web:tng-cdn-uat.who.int:v2:trustlist-ref:DCC:XC","did:web:tng-cdn-uat.who.int:v2:trustlist-ref:DCC:POL","did:web:tng-cdn-uat.who.int:v2:trustlist-ref:DCC:XD","did:web:tng-cdn-uat.who.int:v2:trustlist-ref:DCC:-","did:web:tng-cdn-uat.who.int:v2:trustlist-ref:DCC:XE","did:web:tng-cdn-uat.who.int:v2:trustlist-ref:DCC:CZE","did:web:tng-cdn-uat.who.int:v2:trustlist-ref:DCC:BRA","did:web:tng-cdn-uat.who.int:v2:trustlist-ref:DCC:TUR","did:web:tng-cdn-uat.who.int:v2:trustlist-ref:DCC:OMN","did:web:tng-cdn-uat.who.int:v2:trustlist-ref:DCC:CAN","did:web:tng-cdn-uat.who.int:v2:trustlist-ref:DCC:FRA","did:web:tng-cdn-uat.who.int:v2:trustlist-ref:DCC:LVA","did:web:tng-cdn-uat.who.int:v2:trustlist-ref:DCC:AND","did:web:tng-cdn-uat.who.int:v2:trustlist-ref:DCC:ALB","did:web:tng-cdn-uat.who.int:v2:trustlist-ref:DCC:MCO","did:web:tng-cdn-uat.who.int:v2:trustlist-ref:DCC:SMR","did:web:tng-cdn-uat.who.int:v2:trustlist-ref:DCC:ARM","did:web:tng-cdn-uat.who.int:v2:trustlist-ref:DCC:SGP","did:web:tng-cdn-uat.who.int:v2:trustlist-ref:DCC:TGO","did:web:tng-cdn-uat.who.int:v2:trustlist-ref:DCC:XV","did:web:tng-cdn-dev.who.int:trustlist"],"proof":{"type":"JsonWebSignature2020","created":"2025-09-20T12:00:31Z","nonce":"Cy7ZdsJo8XB2hzbHC8c5IWAVShQwXuLu","proofPurpose":"assertionMethod","verificationMethod":"did:web:raw.githubusercontent.com:WorldHealthOrganization:tng-participants-uat:main:WHO:signing:DID","jws":"eyJiNjQiOmZhbHNlLCJjcml0IjpbImI2NCJdLCJhbGciOiJFUzI1NiJ9..MEUCIQC8jSQkTX5WW0GGquf5XDJvWXflsukzH0JQDoTXsnXyYgIgLBzU2355oadoZ1eJaY4U_gRs2xrEgIjCXK4kxzyMVtU"}}