{"@context":["https://www.w3.org/ns/did/v1","https://w3id.org/security/suites/jws-2020/v1"],"id":"did:web:tng-cdn-uat.who.int:v2:trustlist-ref:DCC:SWE:SCA","controller":"did:web:tng-cdn-uat.who.int:v2:trustlist-ref:DCC:SWE","verificationMethod":["did:web:tng-cdn-uat.who.int:v2:trustlist:DCC:SWE:SCA"],"proof":{"type":"JsonWebSignature2020","created":"2025-09-13T12:00:35Z","nonce":"mXHkSOKR4v11sKTHZGMAjH9JPZGX3gaR","proofPurpose":"assertionMethod","verificationMethod":"did:web:raw.githubusercontent.com:WorldHealthOrganization:tng-participants-uat:main:WHO:signing:DID","jws":"eyJiNjQiOmZhbHNlLCJjcml0IjpbImI2NCJdLCJhbGciOiJFUzI1NiJ9..MEYCIQCMF2ONV6J9Uk0DfJT5ro7HRsz_xYVftbwsWYCs01go9wIhANk3Gosb9Fs4OBebCHfAZnigZeZ9Oddc5sIK-fBr0QyQ"}}