{"@context":["https://www.w3.org/ns/did/v1","https://w3id.org/security/suites/jws-2020/v1"],"id":"did:web:tng-cdn-uat.who.int:v2:trustlist-ref:DCC:TGO:SCA","controller":"did:web:tng-cdn-uat.who.int:v2:trustlist-ref:DCC:TGO","verificationMethod":["did:web:tng-cdn-uat.who.int:v2:trustlist:DCC:TGO:SCA"],"proof":{"type":"JsonWebSignature2020","created":"2025-07-13T06:00:24Z","nonce":"7CyiG9tETKopqTimrmLjTQWyWC0oIfUd","proofPurpose":"assertionMethod","verificationMethod":"did:web:raw.githubusercontent.com:WorldHealthOrganization:tng-participants-uat:main:WHO:signing:DID","jws":"eyJiNjQiOmZhbHNlLCJjcml0IjpbImI2NCJdLCJhbGciOiJFUzI1NiJ9..MEYCIQD7yfKdDqrbhzDZFWtKSXFeIKPH_nzU4nZ5RAErDEaOewIhAI989R3mzYWKVKfZqUjTMaL3nh7Y1iDVCN5lDcT6Z3Vj"}}