{"@context":["https://www.w3.org/ns/did/v1","https://w3id.org/security/suites/jws-2020/v1"],"id":"did:web:tng-cdn-uat.who.int:v2:trustlist-ref:-:WHO","controller":"did:web:tng-cdn-uat.who.int:v2:trustlist-ref:-","verificationMethod":["did:web:tng-cdn-dev.who.int:trustlist"],"proof":{"type":"JsonWebSignature2020","created":"2025-02-08T12:00:00Z","nonce":"8aaj8cpspxDS7hYyKtmC3axiZyzaQTKp","proofPurpose":"assertionMethod","verificationMethod":"did:web:raw.githubusercontent.com:WorldHealthOrganization:tng-participants-uat:main:WHO:signing:DID","jws":"eyJiNjQiOmZhbHNlLCJjcml0IjpbImI2NCJdLCJhbGciOiJFUzI1NiJ9..MEUCIQC2iTSsg_stG3psazThMw0FtyHTLCWtk3R-GbZfe1XlSQIgNEiMOx-62_5Pvt2I022SLaEDwGXjPuS7N_MtgO4UChI"}}