{"@context":["https://www.w3.org/ns/did/v1","https://w3id.org/security/suites/jws-2020/v1"],"id":"did:web:tng-cdn-uat.who.int:v2:trustlist-ref:DCC:BRA:SCA","controller":"did:web:tng-cdn-uat.who.int:v2:trustlist-ref:DCC:BRA","verificationMethod":["did:web:tng-cdn-uat.who.int:v2:trustlist:DCC:BRA:SCA"],"proof":{"type":"JsonWebSignature2020","created":"2026-05-05T00:00:38Z","nonce":"XXvzU6zaVEY1eDXibYblQelys4chrU1k","proofPurpose":"assertionMethod","verificationMethod":"did:web:raw.githubusercontent.com:WorldHealthOrganization:tng-participants-uat:main:WHO:signing:DID","jws":"eyJiNjQiOmZhbHNlLCJjcml0IjpbImI2NCJdLCJhbGciOiJFUzI1NiJ9..MEQCIHA7L6gzV9dODF_VZiqfJ7iGN9bYUdxnyDCX-IKCJIQDAiA1N3mM8dngiF_eZUJ8NviGEd40UL6KhfIb07gzt7iIwQ"}}