{"@context":["https://www.w3.org/ns/did/v1","https://w3id.org/security/suites/jws-2020/v1","https://worldhealthorganization.github.io/smart-trust/tng-additional-context/v1"],"id":"did:web:tng-cdn-uat.who.int:v2:trustlist-ref:DCC:BRA:SCA","controller":"did:web:tng-cdn-uat.who.int:v2:trustlist-ref:DCC:BRA","verificationMethod":["did:web:tng-cdn-uat.who.int:v2:trustlist:DCC:BRA:SCA"],"proof":{"type":"JsonWebSignature2020","created":"2025-12-13T18:00:18Z","nonce":"BrAAbS5JlBzbOSxL7nps7FezUfXRdOlZ","proofPurpose":"assertionMethod","verificationMethod":"did:web:raw.githubusercontent.com:WorldHealthOrganization:tng-participants-uat:main:WHO:signing:DID","jws":"eyJiNjQiOmZhbHNlLCJjcml0IjpbImI2NCJdLCJhbGciOiJFUzI1NiJ9..MEUCIQDZNl89H2_RhNEri3e-V89s_QmaaoGu8yrCP9Xi7dQkAgIgOb9F0AQaGJ17O8msGJxEpAFqYH_PO4X7dp0wNtRGpoc"}}