{"@context":["https://www.w3.org/ns/did/v1","https://w3id.org/security/suites/jws-2020/v1"],"id":"did:web:tng-cdn-uat.who.int:v2:trustlist-ref:-:ESP:DSC","controller":"did:web:tng-cdn-uat.who.int:v2:trustlist-ref:-:ESP","verificationMethod":["did:web:tng-cdn-uat.who.int:v2:trustlist:-:ESP:DSC"],"proof":{"type":"JsonWebSignature2020","created":"2025-11-29T12:00:19Z","nonce":"uIl6EPzr9hkAkvG7ILmOH2L55uLZEubE","proofPurpose":"assertionMethod","verificationMethod":"did:web:raw.githubusercontent.com:WorldHealthOrganization:tng-participants-uat:main:WHO:signing:DID","jws":"eyJiNjQiOmZhbHNlLCJjcml0IjpbImI2NCJdLCJhbGciOiJFUzI1NiJ9..MEUCIQDrxlWGg7_ToAu9N-06Cfz4FwU1ifsh0KiVT0nWlcBuIAIgcCDo6J4CD_v1SV2drO_NHnDNPcn1KxSlZ6WgY8KXM24"}}